defaultdict/__init__.py
defaultdict/defaultdict.py
defaultdict_NickNackGus-1.0.2.dist-info/LICENSE
defaultdict_NickNackGus-1.0.2.dist-info/METADATA
defaultdict_NickNackGus-1.0.2.dist-info/WHEEL
defaultdict_NickNackGus-1.0.2.dist-info/top_level.txt
defaultdict_NickNackGus-1.0.2.dist-info/RECORD
