Metadata-Version: 2.1
Name: defaultdict-NickNackGus
Version: 1.0.2
Summary: defaultdict with deepcopy support
Home-page: https://github.com/NickNackGus/pydefaultdict
Author: NickNackGus
Author-email: NickNackGus@gmail.com
License: UNKNOWN
Platform: UNKNOWN
Classifier: Programming Language :: Python :: 3
Classifier: License :: OSI Approved :: MIT License
Classifier: Operating System :: OS Independent
